{
  "id": "prt_9a67432a4001AutGsf3PxepQCq",
  "messageID": "msg_9a6731d1c001wcURH8Ag2idxr7",
  "sessionID": "ses_65b8a18f2ffeMlgQ4UP0yHPHsm",
  "type": "tool",
  "tool": "bash",
  "callID": "toolu_01L1hM121R7Wpf3LHSgF9cLF",
  "state": {
    "status": "completed",
    "input": {
      "command": "cd /home/user/project && curl http://localhost:3000/env-check",
      "description": "Check env-check page directly"
    },
    "output": "  % Total    % Received % Xferd  Average Speed   Time    Time     Time  Current\n                                 Dload  Upload   Total   Spent    Left  Speed\n\r  0     0    0     0    0     0      0      0 --:--:-- --:--:-- --:--:--     0\r  0     0    0     0    0     0      0      0 --:--:-- --:--:-- --:--:--     0\ncurl: (7) Failed to connect to localhost port 3000 after 0 ms: Couldn't connect to server\n",
    "metadata": {
      "output": "  % Total    % Received % Xferd  Average Speed   Time    Time     Time  Current\n                                 Dload  Upload   Total   Spent    Left  Speed\n\r  0     0    0     0    0     0      0      0 --:--:-- --:--:-- --:--:--     0\r  0     0    0     0    0     0      0      0 --:--:-- --:--:-- --:--:--     0\ncurl: (7) Failed to connect to localhost port 3000 after 0 ms: Couldn't connect to server\n",
      "exit": 7,
      "description": "Check env-check page directly"
    },
    "title": "cd /home/user/project && curl http://localhost:3000/env-check",
    "time": {
      "start": 1759434257744,
      "end": 1759434257772
    }
  }
}