{
  "id": "prt_9a5123ed4001NxFW6CFMe5EACu",
  "messageID": "msg_9a50f4f70001NDySwOToSxsMZR",
  "sessionID": "ses_65b8a18f2ffeMlgQ4UP0yHPHsm",
  "type": "tool",
  "tool": "bash",
  "callID": "toolu_01DUPZfj3BtJMJAuAVxvjVT4",
  "state": {
    "status": "completed",
    "input": {
      "command": "cd /home/user/project && curl -s \"http://localhost:3000/api/auth/providers\"",
      "description": "Test auth providers endpoint without JSON formatting"
    },
    "output": "",
    "metadata": {
      "output": "",
      "exit": 7,
      "description": "Test auth providers endpoint without JSON formatting"
    },
    "title": "cd /home/user/project && curl -s \"http://localhost:3000/api/auth/providers\"",
    "time": {
      "start": 1759411061271,
      "end": 1759411061288
    }
  }
}