{
  "id": "prt_9a62c498e0018XwBH2pf2OVHFy",
  "messageID": "msg_9a62bd5c0001zd4cXQdkG3wMNE",
  "sessionID": "ses_65b8a18f2ffeMlgQ4UP0yHPHsm",
  "type": "text",
  "text": "Perfect! The dev server is now running at **http://localhost:3000**.\n\n## Issue Resolution:\n\n### ✅ **Development Server Started**\n- **URL**: http://localhost:3000\n- **Status**: Ready and running\n- **Environment**: .env loaded correctly\n\n### 🔧 **OAuth Issues to Check**:\n\nThe errors suggest there might be OAuth configuration issues. Let me verify your Google OAuth setup:",
  "time": {
    "start": 1759429544334
  }
}