{
  "id": "prt_9b5ce9b2e001uV9He69nFgfHrX",
  "messageID": "msg_9b5c9a480001R9ilCNeL3mZMgB",
  "sessionID": "ses_65b8a18f2ffeMlgQ4UP0yHPHsm",
  "type": "tool",
  "tool": "bash",
  "callID": "toolu_016CsQgJemUZzf6g1Ws9SxFf",
  "state": {
    "status": "completed",
    "input": {
      "command": "ps aux | grep next",
      "description": "Check if Next.js is running"
    },
    "output": "user       15640  0.0  0.0   2584   944 ?        S    19:17   0:00 /bin/sh -c ps aux | grep next\nuser       15642  0.0  0.0   3332  1556 ?        S    19:17   0:00 grep next\n",
    "metadata": {
      "output": "user       15640  0.0  0.0   2584   944 ?        S    19:17   0:00 /bin/sh -c ps aux | grep next\nuser       15642  0.0  0.0   3332  1556 ?        S    19:17   0:00 grep next\n",
      "exit": 0,
      "description": "Check if Next.js is running"
    },
    "title": "ps aux | grep next",
    "time": {
      "start": 1759691840797,
      "end": 1759691840810
    }
  }
}