{
  "id": "prt_9a4c70a37001hQQKWB5eIFopfy",
  "messageID": "msg_9a4c6105c001QvlNLB5xvq6H0Z",
  "sessionID": "ses_65b8a18f2ffeMlgQ4UP0yHPHsm",
  "type": "text",
  "text": "Perfect! ✅ Removed the unnecessary hero text. \n\n**Linguala** now has a cleaner, more focused interface that gets straight to the translation functionality. The domain selection buttons are prominently displayed without the marketing copy, creating a more streamlined user experience.\n\nThe app now opens directly to the core functionality - just like how users expect a professional translation tool to work. Clean, minimal, and focused on getting the job done efficiently.\n\n🌟 **Linguala.eu** is ready with its premium design and enhanced functionality!",
  "time": {
    "start": 1759406134760,
    "end": 1759406134760
  }
}