{
  "id": "prt_9a4b48fc40028d5xhPHcwPn6gS",
  "messageID": "msg_9a4b0f1960012kMCuOhHt8Mj7Y",
  "sessionID": "ses_65b8a18f2ffeMlgQ4UP0yHPHsm",
  "type": "tool",
  "tool": "todowrite",
  "callID": "toolu_01MbboeYdbUSRnyW8Htpypjq",
  "state": {
    "status": "completed",
    "input": {
      "todos": [
        {
          "content": "Set up Neon PostgreSQL database",
          "status": "completed",
          "priority": "high",
          "id": "setup-neon-db"
        },
        {
          "content": "Configure Auth.js with database adapter",
          "status": "completed",
          "priority": "high",
          "id": "configure-authjs"
        },
        {
          "content": "Create database schema for users, translations, and glossaries",
          "status": "completed",
          "priority": "high",
          "id": "create-db-schema"
        },
        {
          "content": "Add authentication UI components",
          "status": "completed",
          "priority": "medium",
          "id": "auth-ui"
        },
        {
          "content": "Integrate auth with translator features",
          "status": "completed",
          "priority": "medium",
          "id": "integrate-auth"
        }
      ]
    },
    "output": "[\n  {\n    \"content\": \"Set up Neon PostgreSQL database\",\n    \"status\": \"completed\",\n    \"priority\": \"high\",\n    \"id\": \"setup-neon-db\"\n  },\n  {\n    \"content\": \"Configure Auth.js with database adapter\",\n    \"status\": \"completed\",\n    \"priority\": \"high\",\n    \"id\": \"configure-authjs\"\n  },\n  {\n    \"content\": \"Create database schema for users, translations, and glossaries\",\n    \"status\": \"completed\",\n    \"priority\": \"high\",\n    \"id\": \"create-db-schema\"\n  },\n  {\n    \"content\": \"Add authentication UI components\",\n    \"status\": \"completed\",\n    \"priority\": \"medium\",\n    \"id\": \"auth-ui\"\n  },\n  {\n    \"content\": \"Integrate auth with translator features\",\n    \"status\": \"completed\",\n    \"priority\": \"medium\",\n    \"id\": \"integrate-auth\"\n  }\n]",
    "metadata": {
      "todos": [
        {
          "content": "Set up Neon PostgreSQL database",
          "status": "completed",
          "priority": "high",
          "id": "setup-neon-db"
        },
        {
          "content": "Configure Auth.js with database adapter",
          "status": "completed",
          "priority": "high",
          "id": "configure-authjs"
        },
        {
          "content": "Create database schema for users, translations, and glossaries",
          "status": "completed",
          "priority": "high",
          "id": "create-db-schema"
        },
        {
          "content": "Add authentication UI components",
          "status": "completed",
          "priority": "medium",
          "id": "auth-ui"
        },
        {
          "content": "Integrate auth with translator features",
          "status": "completed",
          "priority": "medium",
          "id": "integrate-auth"
        }
      ]
    },
    "title": "0 todos",
    "time": {
      "start": 1759404924112,
      "end": 1759404924112
    }
  }
}