{
  "id": "prt_9a47ae2d90010eUxyhiuXRVIXV",
  "messageID": "msg_9a47920a3001Ot6loJ5a1iylxg",
  "sessionID": "ses_65b8a18f2ffeMlgQ4UP0yHPHsm",
  "type": "tool",
  "tool": "edit",
  "callID": "toolu_01A4s9usZYS2SSiD6oX87nnS",
  "state": {
    "status": "completed",
    "input": {
      "filePath": "/home/user/project/.env",
      "oldString": "# Environment variables\n# Add your environment variables here\n\nDATABASE_URL=\nNEXT_PUBLIC_SUPABASE_URL=\nNEXT_PUBLIC_SUPABASE_ANON_KEY=",
      "newString": "# Environment variables\n# Add your environment variables here\n\n# Translation Service - Required for the DeepL clone\nDASHSCOPE_API_KEY=\n\n# Database (Optional - not used in current DeepL clone)\nDATABASE_URL=\nNEXT_PUBLIC_SUPABASE_URL=\nNEXT_PUBLIC_SUPABASE_ANON_KEY="
    },
    "output": "",
    "metadata": {
      "diagnostics": {},
      "diff": "Index: /home/user/project/.env\n===================================================================\n--- /home/user/project/.env\n+++ /home/user/project/.env\n@@ -1,6 +1,10 @@\n # Environment variables\n # Add your environment variables here\n \n+# Translation Service - Required for the DeepL clone\n+DASHSCOPE_API_KEY=\n+\n+# Database (Optional - not used in current DeepL clone)\n DATABASE_URL=\n NEXT_PUBLIC_SUPABASE_URL=\n NEXT_PUBLIC_SUPABASE_ANON_KEY=\n\\ No newline at end of file\n"
    },
    "title": ".env",
    "time": {
      "start": 1759401143592,
      "end": 1759401143596
    }
  }
}