{
  "id": "prt_9b5c10f70001C6OLkdnokwyLZB",
  "messageID": "msg_9b5bc17dc001nQdxSSC1u5tYv4",
  "sessionID": "ses_65b8a18f2ffeMlgQ4UP0yHPHsm",
  "type": "text",
  "text": "## Step 5: Update Frontend Components\n\nNow I need to update the frontend components to use the correct endpoints:\n\n1. **Translation tab** → calls `/api/translate`\n2. **Write tab** → calls `/api/write` \n3. **Interactive word clicking** → calls `/api/write` for alternatives/rephrase\n\nLet me update the main translator component first:",
  "time": {
    "start": 1759690954700,
    "end": 1759690954700
  }
}